helloG.py
helloG-0.0.1.dist-info/LICENSE.txt
helloG-0.0.1.dist-info/METADATA
helloG-0.0.1.dist-info/WHEEL
helloG-0.0.1.dist-info/top_level.txt
helloG-0.0.1.dist-info/RECORD
