Metadata-Version: 2.1
Name: helloG
Version: 0.0.1
Summary: Say Hello G!
Home-page: UNKNOWN
Author: Quoc Anh
Author-email: zone2120vn@gmail.com
License: UNKNOWN
Platform: UNKNOWN
Classifier: Programming Language :: Python :: 3
Classifier: Operating System :: OS Independent
Requires-Dist: blessings (~=1.7)
